MANIFEST.in
README.txt
setup.cfg
setup.py
pyfinger/__init__.py
pyfinger/command.py
pyfinger/fingerurl.py
pyfinger/foaf.py
pyfinger.egg-info/PKG-INFO
pyfinger.egg-info/SOURCES.txt
pyfinger.egg-info/dependency_links.txt
pyfinger.egg-info/entry_points.txt
pyfinger.egg-info/not-zip-safe
pyfinger.egg-info/top_level.txt
pyfinger/tests/__init__.py
pyfinger/tests/test_urllib2.py