Metadata-Version: 1.0
Name: pyfinger
Version: 0.2
Summary: Python finger program
Home-page: http://packages.python.org/pyfinger
Author: William Waites
Author-email: ww@styx.org
License: BSD
Platform: UNKNOWN
